sources/hiDSPLibs/__init__.py
sources/hiDSPLibs/PYLibs/Loggings.py
sources/hiDSPLibs/PYLibs/__init__.py
sources/hiDSPLibs/PYLibs/images/ImageUtils.py
sources/hiDSPLibs/PYLibs/images/__init__.py
hiDSPLibs-0.0.2.dist-info/LICENSE
hiDSPLibs-0.0.2.dist-info/METADATA
hiDSPLibs-0.0.2.dist-info/WHEEL
hiDSPLibs-0.0.2.dist-info/top_level.txt
hiDSPLibs-0.0.2.dist-info/RECORD
