Metadata-Version: 2.1
Name: hiDSPLibs
Version: 0.0.2
Summary: My DSP Library in Python
Author-email: datnt <datdtbkhn.nguyen@gmail.com>
Classifier: Programming Language :: Python :: 3
Classifier: License :: OSI Approved :: MIT License
Classifier: Operating System :: OS Independent
Requires-Python: >=3.7
License-File: LICENSE
